zmux/__init__.py
zmux/__main__.py
zmux/cli.py
zmux-0.1.dist-info/LICENSE
zmux-0.1.dist-info/METADATA
zmux-0.1.dist-info/WHEEL
zmux-0.1.dist-info/entry_points.txt
zmux-0.1.dist-info/top_level.txt
zmux-0.1.dist-info/RECORD
