Metadata-Version: 2.1
Name: zmux
Version: 0.1
Summary: A tmux parameterizer
Home-page: https://github.com/GregKaleka/zmux
Author: Greg Kaleka
License: Apache License, Version 2.0
Project-URL: Issues, https://github.com/GregKaleka/zmux/issues
Project-URL: CI, https://github.com/GregKaleka/zmux/actions
Project-URL: Changelog, https://github.com/GregKaleka/zmux/releases
Requires-Python: >=3.7
License-File: LICENSE
Requires-Dist: click
Requires-Dist: libtmux
Requires-Dist: yaspin
Provides-Extra: test
Requires-Dist: pytest ; extra == 'test'
